fmeta/__init__.py
fmeta/main.py
fmeta/version.py
fmeta-0.1.4.dist-info/licenses/LICENSE
fmeta-0.1.4.dist-info/METADATA
fmeta-0.1.4.dist-info/WHEEL
fmeta-0.1.4.dist-info/entry_points.txt
fmeta-0.1.4.dist-info/top_level.txt
fmeta-0.1.4.dist-info/RECORD
