Metadata-Version: 2.4
Name: fmeta
Version: 0.1.4
Summary: A small package to scan directories and list file metadata in a tabular format.
Author: Benevant Mathew
Author-email: benevantmathewv@gmail.com
License: MIT
Classifier: Programming Language :: Python :: 3
Classifier: License :: OSI Approved :: MIT License
Classifier: Natural Language :: English
Classifier: Operating System :: OS Independent
Classifier: Topic :: Utilities
Classifier: Topic :: System :: Filesystems
Requires-Python: >=3.7
License-File: LICENSE
Requires-Dist: pandas>=1.3
Dynamic: author
Dynamic: author-email
Dynamic: classifier
Dynamic: description
Dynamic: description-content-type
Dynamic: license
Dynamic: license-file
Dynamic: requires-dist
Dynamic: requires-python
Dynamic: summary
